pyruTorrent/__init__.py
pyruTorrent/pyruTorrent.py
pyrutorrent-1.0.0.dist-info/METADATA
pyrutorrent-1.0.0.dist-info/WHEEL
pyrutorrent-1.0.0.dist-info/RECORD
