Metadata-Version: 2.1
Name: pyruTorrent
Version: 1.0.0
Summary: Simple library for communicating with rTorrent via ruTorrent's httprpc plugin
Project-URL: Homepage, https://github.com/0o120/pyruTorrent
Author-email: 0x78 <contact@0x78.com>
Keywords: api,bittorrent,rtorrent,rutorrent,torrent,xmlrpc
Classifier: Development Status :: 4 - Beta
Classifier: Intended Audience :: Developers
Classifier: License :: OSI Approved :: BSD License
Classifier: Programming Language :: Python :: 3.7
Classifier: Topic :: Communications :: File Sharing
Classifier: Topic :: Software Development :: Libraries :: Python Modules
Requires-Python: >=3.7
Requires-Dist: bencode-py==4.0.0
Requires-Dist: requests
